{
  "schema": 1,
  "product_version": "0.2.3",
  "sources": [
    {
      "component": "ionstack",
      "repository": "https://github.com/yoyicue/xpad2-ionstack-poc",
      "commit": "acb75f8db368278ae258aef2213c5f869c5ddb27",
      "tag": "v1.1.1",
      "license": "GPL-3.0-or-later AND Apache-2.0"
    },
    {
      "component": "ksud-xpad2",
      "repository": "https://github.com/yoyicue/xpad2-ksu-lateload",
      "commit": "9af3e0ea817fcbdf45b9cb08fc8b9bd1910b1cc3",
      "tag": "v0.2.1",
      "artifact": "ksud-xpad2",
      "license": "GPL-3.0-only"
    },
    {
      "component": "ksu-module",
      "repository": "https://github.com/yoyicue/xpad2-ksu-lateload",
      "commit": "9af3e0ea817fcbdf45b9cb08fc8b9bd1910b1cc3",
      "tag": "v0.2.1",
      "artifact": "kernelsu-xpad2-4.19.191.ko",
      "license": "GPL-2.0-only"
    },
    {
      "component": "xpad-installer",
      "repository": "https://github.com/yoyicue/xpad-installer",
      "commit": "679e274ab20c8c8d95679576cb99955ab3b21fc6",
      "tag": "v0.1.1",
      "license": "GPL-3.0-only"
    },
    {
      "component": "kernelsu-manager",
      "repository": "https://github.com/tiann/KernelSU",
      "version": "v3.2.5-22-gccfee6dc",
      "commit": "ccfee6dc67d79a1404eb71c67b67b4f6c7b65a4a",
      "tag": "v3.2.5",
      "tag_commit": "b0bc817b4e966aa6aa830834eaf6ef765d821d40",
      "workflow_run": 29148371657,
      "workflow_artifact": "manager",
      "version_code": 32547,
      "license": "GPL-3.0-only"
    },
    {
      "component": "boominstaller",
      "repository": "https://github.com/yoyicue/BoomInstaller",
      "commit": "29ec1f4b20a262054afe65341206c1d0c726d8c5",
      "tag": "v13.6.0.r11.29ec1f4",
      "license": "Apache-2.0"
    }
  ]
}
